{
  "id": "dl-17-1986",
  "type": "statute",
  "title": "مرسوم بقانون رقم (17) لسنة 1986 بشأن تعديل بعض أحكام قانون الشركات التجارية الصادر بالمرسوم بقانون رقم (28) لسنة 1975",
  "title_en": "Decree No. (20) of 1986 amending of the Social Insurance Law promulgated by Legislative Decree No. (24) of 1976",
  "short_name": "Decree No. (20) of 1986 amending of t...",
  "status": "in_force",
  "issued_date": "",
  "in_force_date": "",
  "url": "https://legalaffairs.gov.bh/Legislation/HTM/L1786",
  "provisions": [],
  "definitions": []
}