{
  "id": "dl-18-1989",
  "type": "statute",
  "title": "مرسوم بقانون رقم (18) لسنة 1989 بفتح إعتماد إضافي في الميزانية العامة للدولة للسنة المالية 1990 وتعديل إعتمادات ميزانية وزارة الدفاع للسنة المالية 1990",
  "title_en": "Decree No (14) of 1989 approving the Accession of the State of Bahrain to the Single Convention on Narcotic Drugs of 1961, as amended by the 1972 Protocol, and to the Convention on Psychotropic Substances of 1971",
  "short_name": "Decree No (14) of 1989 approving the ...",
  "status": "in_force",
  "issued_date": "",
  "in_force_date": "",
  "url": "https://legalaffairs.gov.bh/Legislation/HTM/L1889",
  "provisions": [],
  "definitions": []
}