{
  "id": "dl-3-1999",
  "type": "statute",
  "title": "مرسوم بقانون رقم (3) لسنة 1999 بتعديل بعض أحكام قانون المرافعات المدنية والتجارية الصادر بالمروسم بقانون رقم (12) لسنة 1971",
  "title_en": "Decree No. (26) of 1998 amending certain Provisions of Legislative Decree No. (19) of 1989 regarding the Practice of wholesale Trade by citizens of the Gulf Cooperation Council countries in the State of Bahrain",
  "short_name": "Decree No. (26) of 1998 amending cert...",
  "status": "in_force",
  "issued_date": "",
  "in_force_date": "",
  "url": "https://legalaffairs.gov.bh/Legislation/HTM/L0399",
  "provisions": [],
  "definitions": []
}