{
  "id": "dl-4-1986",
  "type": "statute",
  "title": "مرسوم بقانون رقم (4) لسنة 1986 بشأن الموافقة على إتفاقية إنشاء المؤسسة العامة للجسر السعودي البحريني",
  "title_en": "Decree No. (18) of 1985 approving the Loan Convention to Finance Part of a 66-Volt Substation Cable Project between the Government of the State of Bahrain and the Islamic Development Bank",
  "short_name": "Decree No. (18) of 1985 approving the...",
  "status": "in_force",
  "issued_date": "",
  "in_force_date": "",
  "url": "https://legalaffairs.gov.bh/Legislation/HTM/L0486",
  "provisions": [],
  "definitions": []
}