{
  "id": "dl-75-2006",
  "type": "statute",
  "title": "قانون رقم (75) لسنة 2006 بتعديل بعض أحكام المرسوم بقانون رقم (4) لسنة 1979 بإنشاء بنك الإسكان",
  "title_en": "Law No. (69) of 2006 Ratifying the Agreement on Economic, Commercial and Technical Cooperation between the Government of the Kingdom of Bahrain and the Government of the Republic of Yemen",
  "short_name": "Law No. (69) of 2006 Ratifying the Ag...",
  "status": "in_force",
  "issued_date": "",
  "in_force_date": "",
  "url": "https://legalaffairs.gov.bh/Legislation/HTM/K7506",
  "provisions": [
    {
      "provision_ref": "art17",
      "section": "17",
      "title": "المادة 17",
      "content": "6 - قيام البنك بالمساهمة في شركات قائمة أو بالاشتراك في تأسيس شركات أخرى مع الغير في أية حالة يزيد فيها الارتباط على عشرة ملايين دينار.\nالمادة الثالثة\nيُلغى نص البند (5) من المادة (17) من نظام الشركة المرافق للمرسوم بقانون رقم (4) لسنة 1979 بإنشاء بنك الإسكان.\nالمادة الرابعة\nعلى الوزراء - كل فيما يخصه - تنفيذ أحكام هذا القانون ، ويُعمل به من اليوم التالي لتاريخ نشره في الجريدة الرسمية.\nملك مملكة البحرين\nحمد بن عيسى آل خليفة\nصدر في قصر الرفاع\nبتاريخ: 30 رمضان 1427 ه\nالموافق: 22 أكتوبر 2006 م"
    }
  ],
  "definitions": []
}