{
  "id": "dl-8-1980",
  "type": "statute",
  "title": "مرسوم بقانون رقم (8) لسنة 1980 بتقرير زيادة لأصحاب المعاشات والمستحقين",
  "title_en": "Decree No (5) of 1980 approving the Agreement for Full Ownership of the Rights of Exploration and Production, Facilities and Production Related To It between the Government of the State of Bahrain and the Company of Bahrain Oil Limited",
  "short_name": "Decree No (5) of 1980 approving the A...",
  "status": "in_force",
  "issued_date": "",
  "in_force_date": "",
  "url": "https://legalaffairs.gov.bh/Legislation/HTM/L0880",
  "provisions": [],
  "definitions": []
}