{
  "id": "dl-8-1985",
  "type": "statute",
  "title": "مرسوم بقانون رقم (8) لسنة 1985 بشأن المصادقة على إتفاقية الأمم المتحدة لقانون البحار الموقعة في جاميكا في 10 ديسمبر 1982",
  "title_en": "Decree No. (8) of 1985 regarding the Ratification of the United Nations Convention on the Law of the Sea, signed in Jamaica on 10 December 1982",
  "short_name": "Decree No. (8) of 1985 regarding the ...",
  "status": "in_force",
  "issued_date": "",
  "in_force_date": "",
  "url": "https://legalaffairs.gov.bh/Legislation/HTM/L0885",
  "provisions": [],
  "definitions": []
}