{
  "id": "law-29-2012",
  "type": "statute",
  "title": "قانون رقم (29) لسنة  2012 بالتصديق على بروتوكول تعديل اتفاقية تجنب الازدواج الضريبي ومنع التهرب من الضرائب  بالنسبة للضرائب على الدخل بين حكومة مملكة البحرين وحكومة جمهورية سنغافورة",
  "title_en": "Law No. (29) of 2012 ratifying Protocol Amending the Convention Between the Government of The Kingdom of Bahrain and The Government of the Republic of Singapore for the Avoidance of Double Taxation and the Prevention of Tax Evasion with respect to Taxes on Income&#160;",
  "short_name": "Law No. (29) of 2012 ratifying Protoc...",
  "status": "in_force",
  "issued_date": "",
  "in_force_date": "",
  "url": "https://legalaffairs.gov.bh/Legislation/HTM/K2712",
  "provisions": [],
  "definitions": []
}