{
  "id": "law-42-2005",
  "type": "statute",
  "title": "قانون رقم (42) لسنة 2005 بالتصديق على اتفاق بين حكومة مملكة البحرين وحكومة جمهورية بيلاروس بشأن الخدمات الجوية",
  "title_en": "Law No. (29) of 2005 ratifying the Convention establishing a Free Trade Area between the Countries of the Gulf Cooperation Council and the Republic of Lebanon&#160;",
  "short_name": "Law No. (29) of 2005 ratifying the Co...",
  "status": "in_force",
  "issued_date": "",
  "in_force_date": "",
  "url": "https://legalaffairs.gov.bh/Legislation/HTM/K4205",
  "provisions": [],
  "definitions": []
}